blepcord/__init__.py
blepcord-0.0.1.dist-info/licenses/LICENSE
blepcord-0.0.1.dist-info/METADATA
blepcord-0.0.1.dist-info/WHEEL
blepcord-0.0.1.dist-info/top_level.txt
blepcord-0.0.1.dist-info/RECORD
